LinkedIn_Feed_Bot/LinkedInBot.py
LinkedIn_Feed_Bot/__init__.py
LinkedIn_Feed_Bot/md_to_pdf.py
LinkedIn_Feed_Bot/md_writer.py
LinkedIn_Feed_Bot/utils.py
LinkedIn_Feed_Bot-0.2.0.dist-info/LICENSE
LinkedIn_Feed_Bot-0.2.0.dist-info/METADATA
LinkedIn_Feed_Bot-0.2.0.dist-info/WHEEL
LinkedIn_Feed_Bot-0.2.0.dist-info/top_level.txt
LinkedIn_Feed_Bot-0.2.0.dist-info/RECORD
