Metadata-Version: 2.1
Name: LinkedIn-Feed-Bot
Version: 0.2.0
Summary: LinkedIn Feed crawler with Selenium.
Home-page: https://github.com/Martins6/LinkedIn_Feed_Bot
Author: Adriel Martins
Author-email: am.adriel.martins@gmail.com
License: UNKNOWN
Platform: UNKNOWN
Classifier: Programming Language :: Python :: 3
Classifier: License :: OSI Approved :: GNU General Public License v3 (GPLv3)
Classifier: Operating System :: OS Independent
Requires-Python: >=3.6.0
Requires-Dist: selenium
Requires-Dist: pandas
Requires-Dist: xhtml2pdf
Requires-Dist: markdown
Requires-Dist: webdriver-manager
